gatum_rest_py/GatumRESTAPI.py
gatum_rest_py/__init__.py
gatum_rest_py-1.0.0.dist-info/LICENSE
gatum_rest_py-1.0.0.dist-info/METADATA
gatum_rest_py-1.0.0.dist-info/WHEEL
gatum_rest_py-1.0.0.dist-info/top_level.txt
gatum_rest_py-1.0.0.dist-info/RECORD
